fast_select/CFS.py
fast_select/Chi2.py
fast_select/MDR.py
fast_select/MultiSURF.py
fast_select/ReliefF.py
fast_select/SURF.py
fast_select/TuRF.py
fast_select/__init__.py
fast_select/mRMR.py
fast_select/mutual_information.py
fast_select-0.2.0.dist-info/licenses/LICENSE
fast_select-0.2.0.dist-info/METADATA
fast_select-0.2.0.dist-info/WHEEL
fast_select-0.2.0.dist-info/top_level.txt
fast_select-0.2.0.dist-info/RECORD
