Metadata-Version: 2.4
Name: fast-select
Version: 0.2.0
Summary: A Sci-Kit Learn compatible Numba and CUDA-accelerated implementation of various feature selection algorithms.
Author-email: Gavin Lynch <gavinlynch04@gmail.com>
License-Expression: MIT
Project-URL: Homepage, https://github.com/GavinLynch04/FastSelect
Project-URL: Documentation, https://fastselect.readthedocs.io/en/latest/
Project-URL: Bug Tracker, https://github.com/GavinLynch04/FastSelect/issues
Project-URL: Changelog, https://github.com/GavinLynch04/FastSelect/blob/main/CHANGELOG.md
Keywords: bioinformatics,feature selection,relief,reliefF,machine learning,numba,cuda,gpu,SURF,MultiSURF,TuRF,SURF*,MultiSURF*, mRMR, chi2
Classifier: Development Status :: 4 - Beta
Classifier: Intended Audience :: Science/Research
Classifier: Intended Audience :: Developers
Classifier: Programming Language :: Python :: 3
Classifier: Programming Language :: Python :: 3.9
Classifier: Programming Language :: Python :: 3.10
Classifier: Programming Language :: Python :: 3.11
Classifier: Programming Language :: Python :: 3.12
Classifier: Topic :: Scientific/Engineering :: Bio-Informatics
Classifier: Topic :: Software Development :: Libraries :: Python Modules
Classifier: Topic :: Utilities
Classifier: Operating System :: OS Independent
Classifier: Topic :: Scientific/Engineering :: Artificial Intelligence
Requires-Python: >=3.9
License-File: LICENSE
Requires-Dist: numpy>=1.21
Requires-Dist: numba>=0.56
Requires-Dist: scikit-learn>=1.6
Requires-Dist: pandas
Provides-Extra: gpu
Requires-Dist: cupy-cuda11x; extra == "gpu"
Provides-Extra: test
Requires-Dist: pytest>=7.0; extra == "test"
Requires-Dist: pytest-cov>=4.0; extra == "test"
Requires-Dist: skrebate>=0.6; extra == "test"
Provides-Extra: docs
Provides-Extra: dev
Requires-Dist: fast-select[docs,gpu,test]; extra == "dev"
Requires-Dist: black>=23.0; extra == "dev"
Requires-Dist: ruff>=0.1.0; extra == "dev"
Requires-Dist: twine>=4.0; extra == "dev"
Requires-Dist: sphinx; extra == "dev"
Requires-Dist: furo; extra == "dev"
Requires-Dist: myst-parser; extra == "dev"
Requires-Dist: sphinx-copybutton; extra == "dev"
Dynamic: license-file
